hdd_cdd_calculator/__init__.py
hdd_cdd_calculator/__main__.py
hdd_cdd_calculator/calculator.py
hdd_cdd_calculator/csv_utils.py
hdd_cdd_calculator/data_sources.py
hdd_cdd_calculator/exceptions.py
hdd_cdd_calculator/meteostat_api.py
hdd_cdd_calculator/regression.py
hdd_cdd_calculator/utils.py
hdd_cdd_calculator/visualization.py
hdd_cdd_calculator-0.1.4.dist-info/licenses/LICENSE
hdd_cdd_calculator-0.1.4.dist-info/METADATA
hdd_cdd_calculator-0.1.4.dist-info/WHEEL
hdd_cdd_calculator-0.1.4.dist-info/top_level.txt
hdd_cdd_calculator-0.1.4.dist-info/RECORD
