Metadata-Version: 2.4
Name: hdd-cdd-calculator
Version: 0.1.4
Summary: A Python library for calculating Heating Degree Days (HDD) and Cooling Degree Days (CDD) from multiple weather data sources including the U.S. NWS API and Meteostat, with regression and visualization tools.
Author-email: Ryan Kmetz <consultrmk@gmail.com>
License: MIT
Project-URL: Documentation, https://github.com/rmkenv/hdd_cdd_calculator/tree/main/docs
Project-URL: Source, https://github.com/rmkenv/hdd_cdd_calculator
Project-URL: Tracker, https://github.com/rmkenv/hdd_cdd_calculator/issues
Keywords: HDD,CDD,degree-days,weather,climate,energy,NWS,Meteostat,regression,visualization
Classifier: Development Status :: 4 - Beta
Classifier: Intended Audience :: Developers
Classifier: Intended Audience :: Science/Research
Classifier: Topic :: Scientific/Engineering :: Atmospheric Science
Classifier: License :: OSI Approved :: MIT License
Classifier: Operating System :: OS Independent
Classifier: Programming Language :: Python :: 3
Classifier: Programming Language :: Python :: 3.8
Classifier: Programming Language :: Python :: 3.9
Classifier: Programming Language :: Python :: 3.10
Classifier: Programming Language :: Python :: 3.11
Classifier: Programming Language :: Python :: 3.12
Requires-Python: >=3.8
License-File: LICENSE
Requires-Dist: requests>=2.28
Requires-Dist: pandas>=1.3
Requires-Dist: meteostat>=1.6.5
Requires-Dist: python-dateutil>=2.8
Requires-Dist: scikit-learn>=1.0
Requires-Dist: matplotlib>=3.5
Provides-Extra: dev
Requires-Dist: pytest>=7.0; extra == "dev"
Requires-Dist: black>=23.0; extra == "dev"
Requires-Dist: flake8>=6.0; extra == "dev"
Requires-Dist: mypy>=1.0; extra == "dev"
Provides-Extra: viz
Requires-Dist: matplotlib>=3.5; extra == "viz"
Provides-Extra: tests
Requires-Dist: pytest>=7.0; extra == "tests"
Dynamic: license-file
